scripts/__init__.py
scripts/adb_client.py
scripts/cert_handler.py
scripts/config.json
scripts/config.py
scripts/logger.py
scripts/main.py
scripts/requirements.txt
burpdrop-1.2.0.dist-info/METADATA
burpdrop-1.2.0.dist-info/WHEEL
burpdrop-1.2.0.dist-info/entry_points.txt
burpdrop-1.2.0.dist-info/top_level.txt
burpdrop-1.2.0.dist-info/RECORD
