Metadata-Version: 2.4
Name: burpdrop
Version: 1.2.0
Summary: A cross-platform Burp Suite CA Certificate installer for Android devices
Author-email: Gashaw Kidanu <kidanugashaw@gmail.com>
License: MIT License
Project-URL: Homepage, https://github.com/Gashaw512/android-traffic-interception-guide
Project-URL: Bug Tracker, https://github.com/Gashaw512/android-traffic-interception-guide/issues
Keywords: android,burpsuite,certificate,installer,root,magisk,interception,security
Classifier: Programming Language :: Python :: 3
Classifier: License :: OSI Approved :: MIT License
Classifier: Operating System :: OS Independent
Classifier: Development Status :: 4 - Beta
Classifier: Intended Audience :: Developers
Classifier: Topic :: Security
Classifier: Topic :: Utilities
Requires-Python: >=3.7
Requires-Dist: requests
Requires-Dist: colorama
